metainfo/MetaInfo.py
metainfo/__init__.py
metainfo/environment/DeployedEnvironmentMetaInfo.py
metainfo/environment/DevEnvironmentMetaInfo.py
metainfo/environment/EnvironmentMetaInfo.py
metainfo/environment/__init__.py
metainfo/exception/MetaInfoMissingError.py
metainfo/exception/PackageFileNotFoundError.py
metainfo/exception/__init__.py
persuader_technology_automata_meta_info-0.0.3.dist-info/LICENSE
persuader_technology_automata_meta_info-0.0.3.dist-info/METADATA
persuader_technology_automata_meta_info-0.0.3.dist-info/WHEEL
persuader_technology_automata_meta_info-0.0.3.dist-info/top_level.txt
persuader_technology_automata_meta_info-0.0.3.dist-info/RECORD
