Metadata-Version: 2.1
Name: persuader-technology-automata-meta-info
Version: 0.0.3
Summary: Automata Meta Info
Author: Persuader Technology
Author-email: software@persuader.technology
License: UNLICENSE
Classifier: Programming Language :: Python :: 3
License-File: LICENSE
